<?xml version="1.0" encoding="UTF-8"?>
<Destination_Traffic>
<Destination_Node_Sample>
<From_Time>75600</From_Time>
<To_Time>75899</To_Time>
<Destination_Data>
	<Destination_Node_ID>48526276</Destination_Node_ID>
	<Throughput>101594</Throughput>
</Destination_Data>
<Destination_Data>
	<Destination_Node_ID>50194777</Destination_Node_ID>
	<Throughput>17664</Throughput>
</Destination_Data>
<Destination_Data>
	<Destination_Node_ID>50100190</Destination_Node_ID>
	<Throughput>22</Throughput>
</Destination_Data>
<Destination_Data>
	<Destination_Node_ID>50099195</Destination_Node_ID>
	<Throughput>14</Throughput>
</Destination_Data>
<Destination_Data>
	<Destination_Node_ID>50189178</Destination_Node_ID>
	<Throughput>18</Throughput>
</Destination_Data>
<Destination_Data>
	<Destination_Node_ID>50100309</Destination_Node_ID>
	<Throughput>37</Throughput>
</Destination_Data>
<Destination_Data>
	<Destination_Node_ID>50194390</Destination_Node_ID>
	<Throughput>3966</Throughput>
</Destination_Data>
<Destination_Data>
	<Destination_Node_ID>50099505</Destination_Node_ID>
	<Throughput>50</Throughput>
</Destination_Data>
<Destination_Data>
	<Destination_Node_ID>50190157</Destination_Node_ID>
	<Throughput>7</Throughput>
</Destination_Data>
<Destination_Data>
	<Destination_Node_ID>50097135</Destination_Node_ID>
	<Throughput>25</Throughput>
</Destination_Data>
<Destination_Data>
	<Destination_Node_ID>50194313</Destination_Node_ID>
	<Throughput>16</Throughput>
</Destination_Data>
<Destination_Data>
	<Destination_Node_ID>50097067</Destination_Node_ID>
	<Throughput>11199</Throughput>
</Destination_Data>
<Destination_Data>
	<Destination_Node_ID>50116389</Destination_Node_ID>
	<Throughput>12</Throughput>
</Destination_Data>
<Destination_Data>
	<Destination_Node_ID>310110210</Destination_Node_ID>
	<Throughput>11</Throughput>
</Destination_Data>
<Destination_Data>
	<Destination_Node_ID>50099399</Destination_Node_ID>
	<Throughput>21</Throughput>
</Destination_Data>
<Destination_Data>
	<Destination_Node_ID>50097281</Destination_Node_ID>
	<Throughput>75</Throughput>
</Destination_Data>
<Destination_Data>
	<Destination_Node_ID>308441586</Destination_Node_ID>
	<Throughput>70</Throughput>
</Destination_Data>
<Destination_Data>
	<Destination_Node_ID>308443697</Destination_Node_ID>
	<Throughput>57</Throughput>
</Destination_Data>
<Destination_Data>
	<Destination_Node_ID>48526320</Destination_Node_ID>
	<Throughput>750</Throughput>
</Destination_Data>
</Destination_Node_Sample>
<Destination_Node_Sample>
<From_Time>75900</From_Time>
<To_Time>76199</To_Time>
<Destination_Data>
	<Destination_Node_ID>48526276</Destination_Node_ID>
	<Throughput>101892</Throughput>
</Destination_Data>
<Destination_Data>
	<Destination_Node_ID>50194777</Destination_Node_ID>
	<Throughput>17664</Throughput>
</Destination_Data>
<Destination_Data>
	<Destination_Node_ID>50100190</Destination_Node_ID>
	<Throughput>22</Throughput>
</Destination_Data>
<Destination_Data>
	<Destination_Node_ID>50099195</Destination_Node_ID>
	<Throughput>14</Throughput>
</Destination_Data>
<Destination_Data>
	<Destination_Node_ID>50189178</Destination_Node_ID>
	<Throughput>18</Throughput>
</Destination_Data>
<Destination_Data>
	<Destination_Node_ID>50100309</Destination_Node_ID>
	<Throughput>37</Throughput>
</Destination_Data>
<Destination_Data>
	<Destination_Node_ID>50194390</Destination_Node_ID>
	<Throughput>3966</Throughput>
</Destination_Data>
<Destination_Data>
	<Destination_Node_ID>50099505</Destination_Node_ID>
	<Throughput>50</Throughput>
</Destination_Data>
<Destination_Data>
	<Destination_Node_ID>50190157</Destination_Node_ID>
	<Throughput>7</Throughput>
</Destination_Data>
<Destination_Data>
	<Destination_Node_ID>50097135</Destination_Node_ID>
	<Throughput>25</Throughput>
</Destination_Data>
<Destination_Data>
	<Destination_Node_ID>50194313</Destination_Node_ID>
	<Throughput>16</Throughput>
</Destination_Data>
<Destination_Data>
	<Destination_Node_ID>50097067</Destination_Node_ID>
	<Throughput>11199</Throughput>
</Destination_Data>
<Destination_Data>
	<Destination_Node_ID>50116389</Destination_Node_ID>
	<Throughput>12</Throughput>
</Destination_Data>
<Destination_Data>
	<Destination_Node_ID>310110210</Destination_Node_ID>
	<Throughput>11</Throughput>
</Destination_Data>
<Destination_Data>
	<Destination_Node_ID>50099399</Destination_Node_ID>
	<Throughput>21</Throughput>
</Destination_Data>
<Destination_Data>
	<Destination_Node_ID>50097281</Destination_Node_ID>
	<Throughput>75</Throughput>
</Destination_Data>
<Destination_Data>
	<Destination_Node_ID>308441586</Destination_Node_ID>
	<Throughput>70</Throughput>
</Destination_Data>
<Destination_Data>
	<Destination_Node_ID>308443697</Destination_Node_ID>
	<Throughput>57</Throughput>
</Destination_Data>
<Destination_Data>
	<Destination_Node_ID>48526320</Destination_Node_ID>
	<Throughput>750</Throughput>
</Destination_Data>
</Destination_Node_Sample>
<Destination_Node_Sample>
<From_Time>76200</From_Time>
<To_Time>76499</To_Time>
<Destination_Data>
	<Destination_Node_ID>48526276</Destination_Node_ID>
	<Throughput>102191</Throughput>
</Destination_Data>
<Destination_Data>
	<Destination_Node_ID>50194777</Destination_Node_ID>
	<Throughput>17664</Throughput>
</Destination_Data>
<Destination_Data>
	<Destination_Node_ID>50100190</Destination_Node_ID>
	<Throughput>22</Throughput>
</Destination_Data>
<Destination_Data>
	<Destination_Node_ID>50099195</Destination_Node_ID>
	<Throughput>14</Throughput>
</Destination_Data>
<Destination_Data>
	<Destination_Node_ID>50189178</Destination_Node_ID>
	<Throughput>18</Throughput>
</Destination_Data>
<Destination_Data>
	<Destination_Node_ID>50100309</Destination_Node_ID>
	<Throughput>37</Throughput>
</Destination_Data>
<Destination_Data>
	<Destination_Node_ID>50194390</Destination_Node_ID>
	<Throughput>3966</Throughput>
</Destination_Data>
<Destination_Data>
	<Destination_Node_ID>50099505</Destination_Node_ID>
	<Throughput>50</Throughput>
</Destination_Data>
<Destination_Data>
	<Destination_Node_ID>50190157</Destination_Node_ID>
	<Throughput>7</Throughput>
</Destination_Data>
<Destination_Data>
	<Destination_Node_ID>50097135</Destination_Node_ID>
	<Throughput>25</Throughput>
</Destination_Data>
<Destination_Data>
	<Destination_Node_ID>50194313</Destination_Node_ID>
	<Throughput>16</Throughput>
</Destination_Data>
<Destination_Data>
	<Destination_Node_ID>50097067</Destination_Node_ID>
	<Throughput>11199</Throughput>
</Destination_Data>
<Destination_Data>
	<Destination_Node_ID>50116389</Destination_Node_ID>
	<Throughput>12</Throughput>
</Destination_Data>
<Destination_Data>
	<Destination_Node_ID>310110210</Destination_Node_ID>
	<Throughput>11</Throughput>
</Destination_Data>
<Destination_Data>
	<Destination_Node_ID>50099399</Destination_Node_ID>
	<Throughput>21</Throughput>
</Destination_Data>
<Destination_Data>
	<Destination_Node_ID>50097281</Destination_Node_ID>
	<Throughput>75</Throughput>
</Destination_Data>
<Destination_Data>
	<Destination_Node_ID>308441586</Destination_Node_ID>
	<Throughput>70</Throughput>
</Destination_Data>
<Destination_Data>
	<Destination_Node_ID>308443697</Destination_Node_ID>
	<Throughput>57</Throughput>
</Destination_Data>
<Destination_Data>
	<Destination_Node_ID>48526320</Destination_Node_ID>
	<Throughput>750</Throughput>
</Destination_Data>
</Destination_Node_Sample>
<Destination_Node_Sample>
<From_Time>76500</From_Time>
<To_Time>76799</To_Time>
<Destination_Data>
	<Destination_Node_ID>48526276</Destination_Node_ID>
	<Throughput>102486</Throughput>
</Destination_Data>
<Destination_Data>
	<Destination_Node_ID>50194777</Destination_Node_ID>
	<Throughput>17664</Throughput>
</Destination_Data>
<Destination_Data>
	<Destination_Node_ID>50100190</Destination_Node_ID>
	<Throughput>22</Throughput>
</Destination_Data>
<Destination_Data>
	<Destination_Node_ID>50099195</Destination_Node_ID>
	<Throughput>14</Throughput>
</Destination_Data>
<Destination_Data>
	<Destination_Node_ID>50189178</Destination_Node_ID>
	<Throughput>18</Throughput>
</Destination_Data>
<Destination_Data>
	<Destination_Node_ID>50100309</Destination_Node_ID>
	<Throughput>37</Throughput>
</Destination_Data>
<Destination_Data>
	<Destination_Node_ID>50194390</Destination_Node_ID>
	<Throughput>3966</Throughput>
</Destination_Data>
<Destination_Data>
	<Destination_Node_ID>50099505</Destination_Node_ID>
	<Throughput>50</Throughput>
</Destination_Data>
<Destination_Data>
	<Destination_Node_ID>50190157</Destination_Node_ID>
	<Throughput>7</Throughput>
</Destination_Data>
<Destination_Data>
	<Destination_Node_ID>50097135</Destination_Node_ID>
	<Throughput>25</Throughput>
</Destination_Data>
<Destination_Data>
	<Destination_Node_ID>50194313</Destination_Node_ID>
	<Throughput>16</Throughput>
</Destination_Data>
<Destination_Data>
	<Destination_Node_ID>50097067</Destination_Node_ID>
	<Throughput>11199</Throughput>
</Destination_Data>
<Destination_Data>
	<Destination_Node_ID>50116389</Destination_Node_ID>
	<Throughput>12</Throughput>
</Destination_Data>
<Destination_Data>
	<Destination_Node_ID>310110210</Destination_Node_ID>
	<Throughput>11</Throughput>
</Destination_Data>
<Destination_Data>
	<Destination_Node_ID>50099399</Destination_Node_ID>
	<Throughput>21</Throughput>
</Destination_Data>
<Destination_Data>
	<Destination_Node_ID>50097281</Destination_Node_ID>
	<Throughput>75</Throughput>
</Destination_Data>
<Destination_Data>
	<Destination_Node_ID>308441586</Destination_Node_ID>
	<Throughput>70</Throughput>
</Destination_Data>
<Destination_Data>
	<Destination_Node_ID>308443697</Destination_Node_ID>
	<Throughput>57</Throughput>
</Destination_Data>
<Destination_Data>
	<Destination_Node_ID>48526320</Destination_Node_ID>
	<Throughput>750</Throughput>
</Destination_Data>
</Destination_Node_Sample>
<Destination_Node_Sample>
<From_Time>76800</From_Time>
<To_Time>77099</To_Time>
<Destination_Data>
	<Destination_Node_ID>48526276</Destination_Node_ID>
	<Throughput>102792</Throughput>
</Destination_Data>
<Destination_Data>
	<Destination_Node_ID>50194777</Destination_Node_ID>
	<Throughput>17664</Throughput>
</Destination_Data>
<Destination_Data>
	<Destination_Node_ID>50100190</Destination_Node_ID>
	<Throughput>22</Throughput>
</Destination_Data>
<Destination_Data>
	<Destination_Node_ID>50099195</Destination_Node_ID>
	<Throughput>14</Throughput>
</Destination_Data>
<Destination_Data>
	<Destination_Node_ID>50189178</Destination_Node_ID>
	<Throughput>18</Throughput>
</Destination_Data>
<Destination_Data>
	<Destination_Node_ID>50100309</Destination_Node_ID>
	<Throughput>37</Throughput>
</Destination_Data>
<Destination_Data>
	<Destination_Node_ID>50194390</Destination_Node_ID>
	<Throughput>3966</Throughput>
</Destination_Data>
<Destination_Data>
	<Destination_Node_ID>50099505</Destination_Node_ID>
	<Throughput>50</Throughput>
</Destination_Data>
<Destination_Data>
	<Destination_Node_ID>50190157</Destination_Node_ID>
	<Throughput>7</Throughput>
</Destination_Data>
<Destination_Data>
	<Destination_Node_ID>50097135</Destination_Node_ID>
	<Throughput>25</Throughput>
</Destination_Data>
<Destination_Data>
	<Destination_Node_ID>50194313</Destination_Node_ID>
	<Throughput>16</Throughput>
</Destination_Data>
<Destination_Data>
	<Destination_Node_ID>50097067</Destination_Node_ID>
	<Throughput>11199</Throughput>
</Destination_Data>
<Destination_Data>
	<Destination_Node_ID>50116389</Destination_Node_ID>
	<Throughput>12</Throughput>
</Destination_Data>
<Destination_Data>
	<Destination_Node_ID>310110210</Destination_Node_ID>
	<Throughput>11</Throughput>
</Destination_Data>
<Destination_Data>
	<Destination_Node_ID>50099399</Destination_Node_ID>
	<Throughput>21</Throughput>
</Destination_Data>
<Destination_Data>
	<Destination_Node_ID>50097281</Destination_Node_ID>
	<Throughput>75</Throughput>
</Destination_Data>
<Destination_Data>
	<Destination_Node_ID>308441586</Destination_Node_ID>
	<Throughput>70</Throughput>
</Destination_Data>
<Destination_Data>
	<Destination_Node_ID>308443697</Destination_Node_ID>
	<Throughput>57</Throughput>
</Destination_Data>
<Destination_Data>
	<Destination_Node_ID>48526320</Destination_Node_ID>
	<Throughput>750</Throughput>
</Destination_Data>
</Destination_Node_Sample>
<Destination_Node_Sample>
<From_Time>77100</From_Time>
<To_Time>77399</To_Time>
<Destination_Data>
	<Destination_Node_ID>48526276</Destination_Node_ID>
	<Throughput>103086</Throughput>
</Destination_Data>
<Destination_Data>
	<Destination_Node_ID>50194777</Destination_Node_ID>
	<Throughput>17664</Throughput>
</Destination_Data>
<Destination_Data>
	<Destination_Node_ID>50100190</Destination_Node_ID>
	<Throughput>22</Throughput>
</Destination_Data>
<Destination_Data>
	<Destination_Node_ID>50099195</Destination_Node_ID>
	<Throughput>14</Throughput>
</Destination_Data>
<Destination_Data>
	<Destination_Node_ID>50189178</Destination_Node_ID>
	<Throughput>18</Throughput>
</Destination_Data>
<Destination_Data>
	<Destination_Node_ID>50100309</Destination_Node_ID>
	<Throughput>37</Throughput>
</Destination_Data>
<Destination_Data>
	<Destination_Node_ID>50194390</Destination_Node_ID>
	<Throughput>3966</Throughput>
</Destination_Data>
<Destination_Data>
	<Destination_Node_ID>50099505</Destination_Node_ID>
	<Throughput>50</Throughput>
</Destination_Data>
<Destination_Data>
	<Destination_Node_ID>50190157</Destination_Node_ID>
	<Throughput>7</Throughput>
</Destination_Data>
<Destination_Data>
	<Destination_Node_ID>50097135</Destination_Node_ID>
	<Throughput>25</Throughput>
</Destination_Data>
<Destination_Data>
	<Destination_Node_ID>50194313</Destination_Node_ID>
	<Throughput>16</Throughput>
</Destination_Data>
<Destination_Data>
	<Destination_Node_ID>50097067</Destination_Node_ID>
	<Throughput>11199</Throughput>
</Destination_Data>
<Destination_Data>
	<Destination_Node_ID>50116389</Destination_Node_ID>
	<Throughput>12</Throughput>
</Destination_Data>
<Destination_Data>
	<Destination_Node_ID>310110210</Destination_Node_ID>
	<Throughput>11</Throughput>
</Destination_Data>
<Destination_Data>
	<Destination_Node_ID>50099399</Destination_Node_ID>
	<Throughput>21</Throughput>
</Destination_Data>
<Destination_Data>
	<Destination_Node_ID>50097281</Destination_Node_ID>
	<Throughput>75</Throughput>
</Destination_Data>
<Destination_Data>
	<Destination_Node_ID>308441586</Destination_Node_ID>
	<Throughput>70</Throughput>
</Destination_Data>
<Destination_Data>
	<Destination_Node_ID>308443697</Destination_Node_ID>
	<Throughput>57</Throughput>
</Destination_Data>
<Destination_Data>
	<Destination_Node_ID>48526320</Destination_Node_ID>
	<Throughput>750</Throughput>
</Destination_Data>
</Destination_Node_Sample>
<Destination_Node_Sample>
<From_Time>77400</From_Time>
<To_Time>77699</To_Time>
<Destination_Data>
	<Destination_Node_ID>48526276</Destination_Node_ID>
	<Throughput>103388</Throughput>
</Destination_Data>
<Destination_Data>
	<Destination_Node_ID>50194777</Destination_Node_ID>
	<Throughput>17664</Throughput>
</Destination_Data>
<Destination_Data>
	<Destination_Node_ID>50100190</Destination_Node_ID>
	<Throughput>22</Throughput>
</Destination_Data>
<Destination_Data>
	<Destination_Node_ID>50099195</Destination_Node_ID>
	<Throughput>14</Throughput>
</Destination_Data>
<Destination_Data>
	<Destination_Node_ID>50189178</Destination_Node_ID>
	<Throughput>18</Throughput>
</Destination_Data>
<Destination_Data>
	<Destination_Node_ID>50100309</Destination_Node_ID>
	<Throughput>37</Throughput>
</Destination_Data>
<Destination_Data>
	<Destination_Node_ID>50194390</Destination_Node_ID>
	<Throughput>3966</Throughput>
</Destination_Data>
<Destination_Data>
	<Destination_Node_ID>50099505</Destination_Node_ID>
	<Throughput>50</Throughput>
</Destination_Data>
<Destination_Data>
	<Destination_Node_ID>50190157</Destination_Node_ID>
	<Throughput>7</Throughput>
</Destination_Data>
<Destination_Data>
	<Destination_Node_ID>50097135</Destination_Node_ID>
	<Throughput>25</Throughput>
</Destination_Data>
<Destination_Data>
	<Destination_Node_ID>50194313</Destination_Node_ID>
	<Throughput>16</Throughput>
</Destination_Data>
<Destination_Data>
	<Destination_Node_ID>50097067</Destination_Node_ID>
	<Throughput>11199</Throughput>
</Destination_Data>
<Destination_Data>
	<Destination_Node_ID>50116389</Destination_Node_ID>
	<Throughput>12</Throughput>
</Destination_Data>
<Destination_Data>
	<Destination_Node_ID>310110210</Destination_Node_ID>
	<Throughput>11</Throughput>
</Destination_Data>
<Destination_Data>
	<Destination_Node_ID>50099399</Destination_Node_ID>
	<Throughput>21</Throughput>
</Destination_Data>
<Destination_Data>
	<Destination_Node_ID>50097281</Destination_Node_ID>
	<Throughput>75</Throughput>
</Destination_Data>
<Destination_Data>
	<Destination_Node_ID>308441586</Destination_Node_ID>
	<Throughput>70</Throughput>
</Destination_Data>
<Destination_Data>
	<Destination_Node_ID>308443697</Destination_Node_ID>
	<Throughput>57</Throughput>
</Destination_Data>
<Destination_Data>
	<Destination_Node_ID>48526320</Destination_Node_ID>
	<Throughput>750</Throughput>
</Destination_Data>
</Destination_Node_Sample>
<Destination_Node_Sample>
<From_Time>77700</From_Time>
<To_Time>77999</To_Time>
<Destination_Data>
	<Destination_Node_ID>48526276</Destination_Node_ID>
	<Throughput>103676</Throughput>
</Destination_Data>
<Destination_Data>
	<Destination_Node_ID>50194777</Destination_Node_ID>
	<Throughput>17664</Throughput>
</Destination_Data>
<Destination_Data>
	<Destination_Node_ID>50100190</Destination_Node_ID>
	<Throughput>22</Throughput>
</Destination_Data>
<Destination_Data>
	<Destination_Node_ID>50099195</Destination_Node_ID>
	<Throughput>14</Throughput>
</Destination_Data>
<Destination_Data>
	<Destination_Node_ID>50189178</Destination_Node_ID>
	<Throughput>18</Throughput>
</Destination_Data>
<Destination_Data>
	<Destination_Node_ID>50100309</Destination_Node_ID>
	<Throughput>37</Throughput>
</Destination_Data>
<Destination_Data>
	<Destination_Node_ID>50194390</Destination_Node_ID>
	<Throughput>3966</Throughput>
</Destination_Data>
<Destination_Data>
	<Destination_Node_ID>50099505</Destination_Node_ID>
	<Throughput>50</Throughput>
</Destination_Data>
<Destination_Data>
	<Destination_Node_ID>50190157</Destination_Node_ID>
	<Throughput>7</Throughput>
</Destination_Data>
<Destination_Data>
	<Destination_Node_ID>50097135</Destination_Node_ID>
	<Throughput>25</Throughput>
</Destination_Data>
<Destination_Data>
	<Destination_Node_ID>50194313</Destination_Node_ID>
	<Throughput>16</Throughput>
</Destination_Data>
<Destination_Data>
	<Destination_Node_ID>50097067</Destination_Node_ID>
	<Throughput>11199</Throughput>
</Destination_Data>
<Destination_Data>
	<Destination_Node_ID>50116389</Destination_Node_ID>
	<Throughput>12</Throughput>
</Destination_Data>
<Destination_Data>
	<Destination_Node_ID>310110210</Destination_Node_ID>
	<Throughput>11</Throughput>
</Destination_Data>
<Destination_Data>
	<Destination_Node_ID>50099399</Destination_Node_ID>
	<Throughput>21</Throughput>
</Destination_Data>
<Destination_Data>
	<Destination_Node_ID>50097281</Destination_Node_ID>
	<Throughput>75</Throughput>
</Destination_Data>
<Destination_Data>
	<Destination_Node_ID>308441586</Destination_Node_ID>
	<Throughput>70</Throughput>
</Destination_Data>
<Destination_Data>
	<Destination_Node_ID>308443697</Destination_Node_ID>
	<Throughput>57</Throughput>
</Destination_Data>
<Destination_Data>
	<Destination_Node_ID>48526320</Destination_Node_ID>
	<Throughput>750</Throughput>
</Destination_Data>
</Destination_Node_Sample>
<Destination_Node_Sample>
<From_Time>78000</From_Time>
<To_Time>78299</To_Time>
<Destination_Data>
	<Destination_Node_ID>48526276</Destination_Node_ID>
	<Throughput>103974</Throughput>
</Destination_Data>
<Destination_Data>
	<Destination_Node_ID>50194777</Destination_Node_ID>
	<Throughput>17664</Throughput>
</Destination_Data>
<Destination_Data>
	<Destination_Node_ID>50100190</Destination_Node_ID>
	<Throughput>22</Throughput>
</Destination_Data>
<Destination_Data>
	<Destination_Node_ID>50099195</Destination_Node_ID>
	<Throughput>14</Throughput>
</Destination_Data>
<Destination_Data>
	<Destination_Node_ID>50189178</Destination_Node_ID>
	<Throughput>18</Throughput>
</Destination_Data>
<Destination_Data>
	<Destination_Node_ID>50100309</Destination_Node_ID>
	<Throughput>37</Throughput>
</Destination_Data>
<Destination_Data>
	<Destination_Node_ID>50194390</Destination_Node_ID>
	<Throughput>3966</Throughput>
</Destination_Data>
<Destination_Data>
	<Destination_Node_ID>50099505</Destination_Node_ID>
	<Throughput>50</Throughput>
</Destination_Data>
<Destination_Data>
	<Destination_Node_ID>50190157</Destination_Node_ID>
	<Throughput>7</Throughput>
</Destination_Data>
<Destination_Data>
	<Destination_Node_ID>50097135</Destination_Node_ID>
	<Throughput>25</Throughput>
</Destination_Data>
<Destination_Data>
	<Destination_Node_ID>50194313</Destination_Node_ID>
	<Throughput>16</Throughput>
</Destination_Data>
<Destination_Data>
	<Destination_Node_ID>50097067</Destination_Node_ID>
	<Throughput>11199</Throughput>
</Destination_Data>
<Destination_Data>
	<Destination_Node_ID>50116389</Destination_Node_ID>
	<Throughput>12</Throughput>
</Destination_Data>
<Destination_Data>
	<Destination_Node_ID>310110210</Destination_Node_ID>
	<Throughput>11</Throughput>
</Destination_Data>
<Destination_Data>
	<Destination_Node_ID>50099399</Destination_Node_ID>
	<Throughput>21</Throughput>
</Destination_Data>
<Destination_Data>
	<Destination_Node_ID>50097281</Destination_Node_ID>
	<Throughput>75</Throughput>
</Destination_Data>
<Destination_Data>
	<Destination_Node_ID>308441586</Destination_Node_ID>
	<Throughput>70</Throughput>
</Destination_Data>
<Destination_Data>
	<Destination_Node_ID>308443697</Destination_Node_ID>
	<Throughput>57</Throughput>
</Destination_Data>
<Destination_Data>
	<Destination_Node_ID>48526320</Destination_Node_ID>
	<Throughput>750</Throughput>
</Destination_Data>
</Destination_Node_Sample>
<Destination_Node_Sample>
<From_Time>78300</From_Time>
<To_Time>78599</To_Time>
<Destination_Data>
	<Destination_Node_ID>48526276</Destination_Node_ID>
	<Throughput>104276</Throughput>
</Destination_Data>
<Destination_Data>
	<Destination_Node_ID>50194777</Destination_Node_ID>
	<Throughput>17664</Throughput>
</Destination_Data>
<Destination_Data>
	<Destination_Node_ID>50100190</Destination_Node_ID>
	<Throughput>22</Throughput>
</Destination_Data>
<Destination_Data>
	<Destination_Node_ID>50099195</Destination_Node_ID>
	<Throughput>14</Throughput>
</Destination_Data>
<Destination_Data>
	<Destination_Node_ID>50189178</Destination_Node_ID>
	<Throughput>18</Throughput>
</Destination_Data>
<Destination_Data>
	<Destination_Node_ID>50100309</Destination_Node_ID>
	<Throughput>37</Throughput>
</Destination_Data>
<Destination_Data>
	<Destination_Node_ID>50194390</Destination_Node_ID>
	<Throughput>3966</Throughput>
</Destination_Data>
<Destination_Data>
	<Destination_Node_ID>50099505</Destination_Node_ID>
	<Throughput>50</Throughput>
</Destination_Data>
<Destination_Data>
	<Destination_Node_ID>50190157</Destination_Node_ID>
	<Throughput>7</Throughput>
</Destination_Data>
<Destination_Data>
	<Destination_Node_ID>50097135</Destination_Node_ID>
	<Throughput>25</Throughput>
</Destination_Data>
<Destination_Data>
	<Destination_Node_ID>50194313</Destination_Node_ID>
	<Throughput>16</Throughput>
</Destination_Data>
<Destination_Data>
	<Destination_Node_ID>50097067</Destination_Node_ID>
	<Throughput>11199</Throughput>
</Destination_Data>
<Destination_Data>
	<Destination_Node_ID>50116389</Destination_Node_ID>
	<Throughput>12</Throughput>
</Destination_Data>
<Destination_Data>
	<Destination_Node_ID>310110210</Destination_Node_ID>
	<Throughput>11</Throughput>
</Destination_Data>
<Destination_Data>
	<Destination_Node_ID>50099399</Destination_Node_ID>
	<Throughput>21</Throughput>
</Destination_Data>
<Destination_Data>
	<Destination_Node_ID>50097281</Destination_Node_ID>
	<Throughput>75</Throughput>
</Destination_Data>
<Destination_Data>
	<Destination_Node_ID>308441586</Destination_Node_ID>
	<Throughput>70</Throughput>
</Destination_Data>
<Destination_Data>
	<Destination_Node_ID>308443697</Destination_Node_ID>
	<Throughput>57</Throughput>
</Destination_Data>
<Destination_Data>
	<Destination_Node_ID>48526320</Destination_Node_ID>
	<Throughput>750</Throughput>
</Destination_Data>
</Destination_Node_Sample>
<Destination_Node_Sample>
<From_Time>78600</From_Time>
<To_Time>78899</To_Time>
<Destination_Data>
	<Destination_Node_ID>48526276</Destination_Node_ID>
	<Throughput>104576</Throughput>
</Destination_Data>
<Destination_Data>
	<Destination_Node_ID>50194777</Destination_Node_ID>
	<Throughput>17664</Throughput>
</Destination_Data>
<Destination_Data>
	<Destination_Node_ID>50100190</Destination_Node_ID>
	<Throughput>22</Throughput>
</Destination_Data>
<Destination_Data>
	<Destination_Node_ID>50099195</Destination_Node_ID>
	<Throughput>14</Throughput>
</Destination_Data>
<Destination_Data>
	<Destination_Node_ID>50189178</Destination_Node_ID>
	<Throughput>18</Throughput>
</Destination_Data>
<Destination_Data>
	<Destination_Node_ID>50100309</Destination_Node_ID>
	<Throughput>37</Throughput>
</Destination_Data>
<Destination_Data>
	<Destination_Node_ID>50194390</Destination_Node_ID>
	<Throughput>3966</Throughput>
</Destination_Data>
<Destination_Data>
	<Destination_Node_ID>50099505</Destination_Node_ID>
	<Throughput>50</Throughput>
</Destination_Data>
<Destination_Data>
	<Destination_Node_ID>50190157</Destination_Node_ID>
	<Throughput>7</Throughput>
</Destination_Data>
<Destination_Data>
	<Destination_Node_ID>50097135</Destination_Node_ID>
	<Throughput>25</Throughput>
</Destination_Data>
<Destination_Data>
	<Destination_Node_ID>50194313</Destination_Node_ID>
	<Throughput>16</Throughput>
</Destination_Data>
<Destination_Data>
	<Destination_Node_ID>50097067</Destination_Node_ID>
	<Throughput>11199</Throughput>
</Destination_Data>
<Destination_Data>
	<Destination_Node_ID>50116389</Destination_Node_ID>
	<Throughput>12</Throughput>
</Destination_Data>
<Destination_Data>
	<Destination_Node_ID>310110210</Destination_Node_ID>
	<Throughput>11</Throughput>
</Destination_Data>
<Destination_Data>
	<Destination_Node_ID>50099399</Destination_Node_ID>
	<Throughput>21</Throughput>
</Destination_Data>
<Destination_Data>
	<Destination_Node_ID>50097281</Destination_Node_ID>
	<Throughput>75</Throughput>
</Destination_Data>
<Destination_Data>
	<Destination_Node_ID>308441586</Destination_Node_ID>
	<Throughput>70</Throughput>
</Destination_Data>
<Destination_Data>
	<Destination_Node_ID>308443697</Destination_Node_ID>
	<Throughput>57</Throughput>
</Destination_Data>
<Destination_Data>
	<Destination_Node_ID>48526320</Destination_Node_ID>
	<Throughput>750</Throughput>
</Destination_Data>
</Destination_Node_Sample>
<Destination_Node_Sample>
<From_Time>78900</From_Time>
<To_Time>79199</To_Time>
<Destination_Data>
	<Destination_Node_ID>48526276</Destination_Node_ID>
	<Throughput>104864</Throughput>
</Destination_Data>
<Destination_Data>
	<Destination_Node_ID>50194777</Destination_Node_ID>
	<Throughput>17664</Throughput>
</Destination_Data>
<Destination_Data>
	<Destination_Node_ID>50100190</Destination_Node_ID>
	<Throughput>22</Throughput>
</Destination_Data>
<Destination_Data>
	<Destination_Node_ID>50099195</Destination_Node_ID>
	<Throughput>14</Throughput>
</Destination_Data>
<Destination_Data>
	<Destination_Node_ID>50189178</Destination_Node_ID>
	<Throughput>18</Throughput>
</Destination_Data>
<Destination_Data>
	<Destination_Node_ID>50100309</Destination_Node_ID>
	<Throughput>37</Throughput>
</Destination_Data>
<Destination_Data>
	<Destination_Node_ID>50194390</Destination_Node_ID>
	<Throughput>3966</Throughput>
</Destination_Data>
<Destination_Data>
	<Destination_Node_ID>50099505</Destination_Node_ID>
	<Throughput>50</Throughput>
</Destination_Data>
<Destination_Data>
	<Destination_Node_ID>50190157</Destination_Node_ID>
	<Throughput>7</Throughput>
</Destination_Data>
<Destination_Data>
	<Destination_Node_ID>50097135</Destination_Node_ID>
	<Throughput>25</Throughput>
</Destination_Data>
<Destination_Data>
	<Destination_Node_ID>50194313</Destination_Node_ID>
	<Throughput>16</Throughput>
</Destination_Data>
<Destination_Data>
	<Destination_Node_ID>50097067</Destination_Node_ID>
	<Throughput>11199</Throughput>
</Destination_Data>
<Destination_Data>
	<Destination_Node_ID>50116389</Destination_Node_ID>
	<Throughput>12</Throughput>
</Destination_Data>
<Destination_Data>
	<Destination_Node_ID>310110210</Destination_Node_ID>
	<Throughput>11</Throughput>
</Destination_Data>
<Destination_Data>
	<Destination_Node_ID>50099399</Destination_Node_ID>
	<Throughput>21</Throughput>
</Destination_Data>
<Destination_Data>
	<Destination_Node_ID>50097281</Destination_Node_ID>
	<Throughput>75</Throughput>
</Destination_Data>
<Destination_Data>
	<Destination_Node_ID>308441586</Destination_Node_ID>
	<Throughput>70</Throughput>
</Destination_Data>
<Destination_Data>
	<Destination_Node_ID>308443697</Destination_Node_ID>
	<Throughput>57</Throughput>
</Destination_Data>
<Destination_Data>
	<Destination_Node_ID>48526320</Destination_Node_ID>
	<Throughput>750</Throughput>
</Destination_Data>
</Destination_Node_Sample>
</Destination_Traffic>
